<?xml version="1.0" standalone="yes"?>
<?xml-stylesheet href="x2script.xsl" type="text/xsl"?>
<!-- Generated using X-Studio -->
<script>
	<name>tv.get.global</name>
	<version>1</version>
	<engineversion>50</engineversion>
	<description></description>
	<arguments>
		<argument index="1" name="name" type="Var/String" desc="The name of the global variable to get" />
	</arguments>
	<sourcetext>
		<line linenr="001" indent="">
			<comment>* Returns the value of the global variable to get</comment>
		</line>
		<line linenr="002" indent="">
			<comment>* $name = string - the global variable to get </comment>
		</line>
		<line linenr="003" indent="" />
		<line linenr="004" indent="">
			<var>$globals</var>
			<text> </text>
			<text>=</text>
			<text> </text>
			<text>get</text>
			<text> </text>
			<text>global</text>
			<text> </text>
			<text>variable</text>
			<text>:</text>
			<text> </text>
			<text>name</text>
			<text>=</text>
			<text>'tv.globals'</text>
		</line>
		<line linenr="005" indent="" />
		<line linenr="006" indent="">
			<var>$value</var>
			<text> </text>
			<text>=</text>
			<text> </text>
			<text>table</text>
			<text> </text>
			<text>get</text>
			<text> </text>
			<var>$globals</var>
			<text> </text>
			<text>(</text>
			<text> </text>
			<var>$name</var>
			<text> </text>
			<text>)</text>
		</line>
		<line linenr="007" indent="" />
		<line linenr="008" indent="">
			<text>return</text>
			<text> </text>
			<var>$value</var>
		</line>
		<line linenr="009" indent="" />
	</sourcetext>
	<codearray>
		<sval type="array" size="10">
			<sval type="string" val="tv.get.global" />
			<sval type="int" val="50" />
			<sval type="string" val="" />
			<sval type="int" val="1" />
			<sval type="int" val="0" />
			<sval type="array" size="3">
				<sval type="string" val="name" />
				<sval type="string" val="globals" />
				<sval type="string" val="value" />
			</sval>
			<sval type="array" size="3">
				<sval type="array" size="4">
					<sval type="int" val="158" />
					<sval type="int" val="5" />
					<sval type="string" val="tv.globals" />
					<sval type="int" val="1" />
				</sval>
				<sval type="array" size="6">
					<sval type="int" val="1709" />
					<sval type="int" val="2" />
					<sval type="int" val="131074" />
					<sval type="int" val="1" />
					<sval type="int" val="131074" />
					<sval type="int" val="0" />
				</sval>
				<sval type="array" size="3">
					<sval type="int" val="103" />
					<sval type="int" val="131074" />
					<sval type="int" val="2" />
				</sval>
			</sval>
			<sval type="array" size="1">
				<sval type="array" size="2">
					<sval type="int" val="11" />
					<sval type="string" val="The name of the global variable to get" />
				</sval>
			</sval>
			<sval type="array" size="6">
				<sval type="array" size="3">
					<sval type="int" val="0" />
					<sval type="int" val="1" />
					<sval type="string" val="Returns the value of the global variable to get" />
				</sval>
				<sval type="array" size="3">
					<sval type="int" val="0" />
					<sval type="int" val="1" />
					<sval type="string" val="$name = string - the global variable to get " />
				</sval>
				<sval type="array" size="2">
					<sval type="int" val="0" />
					<sval type="int" val="2" />
				</sval>
				<sval type="array" size="2">
					<sval type="int" val="1" />
					<sval type="int" val="2" />
				</sval>
				<sval type="array" size="2">
					<sval type="int" val="2" />
					<sval type="int" val="2" />
				</sval>
				<sval type="array" size="2">
					<sval type="int" val="3" />
					<sval type="int" val="2" />
				</sval>
			</sval>
			<sval type="int" val="0" />
		</sval>
	</codearray>
</script>
